everlib/__init__.py
everlib/__main__.py
everlib/cli.py
everlib-0.0.1.dist-info/LICENSE-APACHE
everlib-0.0.1.dist-info/LICENSE-MIT
everlib-0.0.1.dist-info/METADATA
everlib-0.0.1.dist-info/WHEEL
everlib-0.0.1.dist-info/entry_points.txt
everlib-0.0.1.dist-info/top_level.txt
everlib-0.0.1.dist-info/RECORD
