Metadata-Version: 2.1
Name: everlib
Version: 0.0.1
Summary: Everlasting media library backed by cloud storage
Home-page: https://github.com/ofek/everlib
Author: Ofek Lev
Author-email: ofekmeister@gmail.com
License: Apache-2.0 OR MIT
Project-URL: Documentation, https://ofek.dev/everlib
Project-URL: Source Code, https://github.com/ofek/everlib
Project-URL: Bug Tracker, https://github.com/ofek/everlib/issues
Keywords: plex,calibre,media,kubernetes,cloud,storage,filesystem
Platform: UNKNOWN
Classifier: Development Status :: 4 - Beta
Classifier: Environment :: Console
Classifier: Intended Audience :: End Users/Desktop
Classifier: License :: OSI Approved :: Apache Software License
Classifier: License :: OSI Approved :: MIT License
Classifier: Natural Language :: English
Classifier: Operating System :: OS Independent
Classifier: Programming Language :: Python
Classifier: Programming Language :: Python :: 3 :: Only
Classifier: Programming Language :: Python :: 3.6
Classifier: Programming Language :: Python :: 3.7
Classifier: Programming Language :: Python :: 3.8
Classifier: Programming Language :: Python :: Implementation :: CPython
Classifier: Programming Language :: Python :: Implementation :: PyPy
Classifier: Topic :: Multimedia
Classifier: Topic :: System :: Archiving :: Mirroring
Classifier: Topic :: System :: Filesystems
Classifier: Topic :: Utilities
Requires-Python: >=3.6
Requires-Dist: appdirs
Requires-Dist: atomicwrites
Requires-Dist: binary
Requires-Dist: click
Requires-Dist: colorama
Requires-Dist: pyperclip (>=1.7.0)
Requires-Dist: pytz (>=2018.7)
Requires-Dist: PyYAML (>=3.13)
Requires-Dist: requests
Requires-Dist: toml (>=0.10.0)
Requires-Dist: tzlocal (>=1.5.1)
